{
     "type": "ServerProfileV12",
     "uri": "/rest/server-profiles/3c244628-0a0d-4ccd-a137-b77f639fe266",
     "profileUUID": "3c244628-0a0d-4ccd-a137-b77f639fe266",
     "name": "Syn108Clu-node1",
     "description": "",
     "serialNumber": "VCGWGIH03B",
     "uuid": "3c244628-0a0d-4ccd-a137-b77f639fe266",
     "iscsiInitiatorName": "iqn.2015-02.com.hpe:oneview-vcgwgih03b",
     "iscsiInitiatorNameType": "AutoGenerated",
     "serverProfileTemplateUri": "/rest/server-profile-templates/67cfe4af-a770-4ffd-9faa-4e2d6ab213cb",
     "templateCompliance": "Compliant",
     "serverHardwareUri": "/rest/server-hardware/39313738-3034-584D-5130-303930303639",
     "serverHardwareTypeUri": "/rest/server-hardware-types/6B5CA934-D18C-4C08-8176-6094340734F6",
     "enclosureGroupUri": "/rest/enclosure-groups/a02d0a91-711a-4f52-9712-dd36e187934e",
     "enclosureUri": "/rest/enclosures/P06011MXQ01403V1",
     "enclosureBay": 1,
     "affinity": "Bay",
     "associatedServer": "MXQ0090069",
     "hideUnusedFlexNics": true,
     "firmware": {
          "firmwareBaselineUri": "/rest/firmware-drivers/Synergy_Service_Pack_SSP_2021_11_01_Z7550-97261",
          "manageFirmware": true,
          "forceInstallFirmware": false,
          "firmwareInstallType": "FirmwareOnly",
          "firmwareScheduleDateTime": "",
          "firmwareActivationType": "Immediate",
          "reapplyState": "NotApplying",
          "consistencyState": "Inconsistent"
     },
     "macType": "Virtual",
     "wwnType": "Virtual",
     "serialNumberType": "Virtual",
     "category": "server-profiles",
     "created": "2022-01-25T16:07:17.190Z",
     "modified": "2022-02-01T02:23:06.740Z",
     "status": "OK",
     "state": "Normal",
     "serverHardwareReapplyState": "NotApplying",
     "inProgress": false,
     "taskUri": "/rest/tasks/bf173923-0b71-4a5a-8c43-d23f6a74bb41",
     "connectionSettings": {
          "reapplyState": "NotApplying",
          "connections": [
               {
                    "id": 1,
                    "name": "SET1",
                    "functionType": "Ethernet",
                    "networkUri": "/rest/network-sets/e4882ebb-4a4b-46e0-8869-c6a06044953d",
                    "portId": "Mezz 3:1-a",
                    "requestedVFs": "0",
                    "allocatedVFs": 0,
                    "interconnectUri": "/rest/interconnects/a889149a-ceac-4ca0-b299-47bfac901195",
                    "macType": "Virtual",
                    "wwpnType": "Virtual",
                    "mac": "7A:52:A9:30:02:05",
                    "wwnn": null,
                    "wwpn": null,
                    "requestedMbps": "2500",
                    "allocatedMbps": 2500,
                    "maximumMbps": 50000,
                    "ipv4": null,
                    "boot": {
                         "priority": "NotBootable"
                    },
                    "state": "Deployed",
                    "status": "OK",
                    "managed": true,
                    "networkName": null,
                    "lagName": null,
                    "interconnectPort": 1,
                    "isolatedTrunk": false,
                    "privateVlanPortType": "None"
               },
               {
                    "id": 2,
                    "name": "SET2",
                    "functionType": "Ethernet",
                    "networkUri": "/rest/network-sets/e4882ebb-4a4b-46e0-8869-c6a06044953d",
                    "portId": "Mezz 3:2-a",
                    "requestedVFs": "0",
                    "allocatedVFs": 0,
                    "interconnectUri": "/rest/interconnects/17a21b98-92a9-47cc-965d-ce97f6706816",
                    "macType": "Virtual",
                    "wwpnType": "Virtual",
                    "mac": "7A:52:A9:30:02:07",
                    "wwnn": null,
                    "wwpn": null,
                    "requestedMbps": "2500",
                    "allocatedMbps": 2500,
                    "maximumMbps": 50000,
                    "ipv4": null,
                    "boot": {
                         "priority": "NotBootable"
                    },
                    "state": "Deployed",
                    "status": "OK",
                    "managed": true,
                    "networkName": null,
                    "lagName": null,
                    "interconnectPort": 13,
                    "isolatedTrunk": false,
                    "privateVlanPortType": "None"
               },
               {
                    "id": 3,
                    "name": "Vmotion1",
                    "functionType": "Ethernet",
                    "networkUri": "/rest/ethernet-networks/aaadf889-0d71-4b19-a454-9824859adbe2",
                    "portId": "Mezz 3:1-d",
                    "requestedVFs": "0",
                    "allocatedVFs": 0,
                    "interconnectUri": "/rest/interconnects/a889149a-ceac-4ca0-b299-47bfac901195",
                    "macType": "Virtual",
                    "wwpnType": "Virtual",
                    "mac": "7A:52:A9:30:02:09",
                    "wwnn": null,
                    "wwpn": null,
                    "requestedMbps": "2500",
                    "allocatedMbps": 2500,
                    "maximumMbps": 50000,
                    "ipv4": null,
                    "boot": {
                         "priority": "NotBootable"
                    },
                    "state": "Deployed",
                    "status": "OK",
                    "managed": true,
                    "networkName": null,
                    "lagName": null,
                    "interconnectPort": 1,
                    "isolatedTrunk": false,
                    "privateVlanPortType": "None"
               },
               {
                    "id": 4,
                    "name": "Vmotion2",
                    "functionType": "Ethernet",
                    "networkUri": "/rest/ethernet-networks/aaadf889-0d71-4b19-a454-9824859adbe2",
                    "portId": "Mezz 3:2-d",
                    "requestedVFs": "0",
                    "allocatedVFs": 0,
                    "interconnectUri": "/rest/interconnects/17a21b98-92a9-47cc-965d-ce97f6706816",
                    "macType": "Virtual",
                    "wwpnType": "Virtual",
                    "mac": "7A:52:A9:30:02:0B",
                    "wwnn": null,
                    "wwpn": null,
                    "requestedMbps": "2500",
                    "allocatedMbps": 2500,
                    "maximumMbps": 50000,
                    "ipv4": null,
                    "boot": {
                         "priority": "NotBootable"
                    },
                    "state": "Deployed",
                    "status": "OK",
                    "managed": true,
                    "networkName": null,
                    "lagName": null,
                    "interconnectPort": 13,
                    "isolatedTrunk": false,
                    "privateVlanPortType": "None"
               },
               {
                    "id": 9,
                    "name": "SAN-A",
                    "functionType": "FibreChannel",
                    "networkUri": "/rest/fc-networks/a2becbfc-e2aa-4c3f-b19a-722cf3f479a8",
                    "portId": "Mezz 3:1-b",
                    "requestedVFs": null,
                    "allocatedVFs": null,
                    "interconnectUri": "/rest/interconnects/a889149a-ceac-4ca0-b299-47bfac901195",
                    "macType": "Virtual",
                    "wwpnType": "Virtual",
                    "mac": "7A:52:A9:30:02:0D",
                    "wwnn": "10:00:DA:E7:D5:50:00:D7",
                    "wwpn": "10:00:DA:E7:D5:50:00:D6",
                    "requestedMbps": "2500",
                    "allocatedMbps": 2500,
                    "maximumMbps": 50000,
                    "ipv4": null,
                    "boot": {
                         "priority": "NotBootable"
                    },
                    "state": "Deployed",
                    "status": "OK",
                    "managed": true,
                    "networkName": null,
                    "lagName": null,
                    "interconnectPort": 1,
                    "isolatedTrunk": false,
                    "privateVlanPortType": "None"
               },
               {
                    "id": 10,
                    "name": "SAN-B",
                    "functionType": "FibreChannel",
                    "networkUri": "/rest/fc-networks/210aa2a0-5d6c-4f4d-b390-ac2f8dc1de75",
                    "portId": "Mezz 3:2-b",
                    "requestedVFs": null,
                    "allocatedVFs": null,
                    "interconnectUri": "/rest/interconnects/17a21b98-92a9-47cc-965d-ce97f6706816",
                    "macType": "Virtual",
                    "wwpnType": "Virtual",
                    "mac": "7A:52:A9:30:02:0F",
                    "wwnn": "10:00:DA:E7:D5:50:00:DB",
                    "wwpn": "10:00:DA:E7:D5:50:00:DA",
                    "requestedMbps": "2500",
                    "allocatedMbps": 2500,
                    "maximumMbps": 50000,
                    "ipv4": null,
                    "boot": {
                         "priority": "NotBootable"
                    },
                    "state": "Deployed",
                    "status": "OK",
                    "managed": true,
                    "networkName": null,
                    "lagName": null,
                    "interconnectPort": 13,
                    "isolatedTrunk": false,
                    "privateVlanPortType": "None"
               }
          ]
     },
     "bootMode": {
          "manageMode": true,
          "mode": "UEFIOptimized",
          "pxeBootPolicy": "Auto",
          "secureBoot": "Unmanaged"
     },
     "boot": {
          "manageBoot": true,
          "order": [
               "HardDisk"
          ]
     },
     "bios": {
          "manageBios": true,
          "overriddenSettings": [
               {
                    "id": "MinProcIdlePower",
                    "value": "NoCStates"
               },
               {
                    "id": "IntelUpiPowerManagement",
                    "value": "Disabled"
               },
               {
                    "id": "AdvancedMemProtection",
                    "value": "FastFaultTolerantADDDC"
               },
               {
                    "id": "MinProcIdlePkgState",
                    "value": "NoState"
               },
               {
                    "id": "EnergyPerfBias",
                    "value": "MaxPerf"
               },
               {
                    "id": "UncoreFreqScaling",
                    "value": "Maximum"
               },
               {
                    "id": "PowerRegulator",
                    "value": "StaticHighPerf"
               },
               {
                    "id": "EmbeddedSata",
                    "value": "Ahci"
               },
               {
                    "id": "EnergyEfficientTurbo",
                    "value": "Disabled"
               },
               {
                    "id": "NumaGroupSizeOpt",
                    "value": "Clustered"
               },
               {
                    "id": "SubNumaClustering",
                    "value": "Enabled"
               },
               {
                    "id": "CollabPowerControl",
                    "value": "Disabled"
               },
               {
                    "id": "WorkloadProfile",
                    "value": "Virtualization-MaxPerformance"
               }
          ],
          "reapplyState": "NotApplying",
          "consistencyState": "Consistent"
     },
     "managementProcessor": {
          "reapplyState": "NotApplying",
          "manageMp": false,
          "mpSettings": []
     },
     "localStorage": {
          "sasLogicalJBODs": [],
          "controllers": [
               {
                    "deviceSlot": "Embedded",
                    "mode": "Mixed",
                    "initialize": false,
                    "importConfiguration": false,
                    "driveWriteCache": "Unmanaged",
                    "predictiveSpareRebuild": "Unmanaged",
                    "logicalDrives": [
                         {
                              "name": "Boot",
                              "raidLevel": "RAID1",
                              "bootable": true,
                              "numPhysicalDrives": 2,
                              "driveTechnology": null,
                              "sasLogicalJBODId": null,
                              "accelerator": "Unmanaged",
                              "numSpareDrives": null,
                              "driveNumber": 1
                         }
                    ]
               }
          ],
          "reapplyState": "NotApplying"
     },
     "sanStorage": {
          "hostOSType": "VMware (ESXi)",
          "manageSanStorage": true,
          "volumeAttachments": [
               {
                    "id": 2,
                    "lun": "1",
                    "lunType": "Auto",
                    "status": "OK",
                    "volumeUri": "/rest/storage-volumes/B3CF3500-B4BF-4A4F-AA02-ADF7011E5034",
                    "volumeStorageSystemUri": "/rest/storage-systems/dd648021-5877-47dd-928f-adf700d7d8ac",
                    "associatedTemplateAttachmentId": "d438cccf-bc43-4c27-ad95-404ac61b7102",
                    "bootVolumePriority": "NotBootable",
                    "isPermanent": true,
                    "state": "Attached",
                    "storagePaths": [
                         {
                              "connectionId": 9,
                              "status": "OK",
                              "networkUri": "/rest/fc-networks/a2becbfc-e2aa-4c3f-b19a-722cf3f479a8",
                              "targetSelector": "Auto",
                              "targets": [
                                   {
                                        "name": "20:32:00:02:AC:02:54:04"
                                   },
                                   {
                                        "name": "21:42:00:02:AC:02:54:04"
                                   },
                                   {
                                        "name": "21:32:00:02:AC:02:54:04"
                                   },
                                   {
                                        "name": "20:42:00:02:AC:02:54:04"
                                   }
                              ],
                              "isEnabled": true
                         },
                         {
                              "connectionId": 10,
                              "status": "OK",
                              "networkUri": "/rest/fc-networks/210aa2a0-5d6c-4f4d-b390-ac2f8dc1de75",
                              "targetSelector": "Auto",
                              "targets": [
                                   {
                                        "name": "20:32:00:02:AC:02:54:04"
                                   },
                                   {
                                        "name": "21:42:00:02:AC:02:54:04"
                                   },
                                   {
                                        "name": "21:32:00:02:AC:02:54:04"
                                   },
                                   {
                                        "name": "20:42:00:02:AC:02:54:04"
                                   }
                              ],
                              "isEnabled": true
                         }
                    ],
                    "volume": null
               },
               {
                    "id": 3,
                    "lun": "2",
                    "lunType": "Auto",
                    "status": "OK",
                    "volumeUri": "/rest/storage-volumes/BF0545F8-5FC2-4C69-B4BA-AE2B012B8BB5",
                    "volumeStorageSystemUri": "/rest/storage-systems/dd648021-5877-47dd-928f-adf700d7d8ac",
                    "associatedTemplateAttachmentId": "f8eab8fb-32ec-44a3-9496-9ae6451e92c2",
                    "bootVolumePriority": "NotBootable",
                    "isPermanent": true,
                    "state": "Attached",
                    "storagePaths": [
                         {
                              "connectionId": 9,
                              "status": "OK",
                              "networkUri": "/rest/fc-networks/a2becbfc-e2aa-4c3f-b19a-722cf3f479a8",
                              "targetSelector": "Auto",
                              "targets": [
                                   {
                                        "name": "20:32:00:02:AC:02:54:04"
                                   },
                                   {
                                        "name": "21:42:00:02:AC:02:54:04"
                                   },
                                   {
                                        "name": "21:32:00:02:AC:02:54:04"
                                   },
                                   {
                                        "name": "20:42:00:02:AC:02:54:04"
                                   }
                              ],
                              "isEnabled": true
                         },
                         {
                              "connectionId": 10,
                              "status": "OK",
                              "networkUri": "/rest/fc-networks/210aa2a0-5d6c-4f4d-b390-ac2f8dc1de75",
                              "targetSelector": "Auto",
                              "targets": [
                                   {
                                        "name": "20:32:00:02:AC:02:54:04"
                                   },
                                   {
                                        "name": "21:42:00:02:AC:02:54:04"
                                   },
                                   {
                                        "name": "21:32:00:02:AC:02:54:04"
                                   },
                                   {
                                        "name": "20:42:00:02:AC:02:54:04"
                                   }
                              ],
                              "isEnabled": true
                         }
                    ],
                    "volume": null
               }
          ],
          "sanSystemCredentials": [],
          "secretsGenerated": "Unknown",
          "reapplyState": "NotApplying"
     },
     "osDeploymentSettings": {
          "osDeploymentPlanUri": null,
          "osVolumeUri": null,
          "forceOsDeployment": false,
          "osCustomAttributes": [],
          "reapplyState": "NotApplying",
          "deployMethod": null,
          "deploymentPortId": null,
          "deploymentMac": null
     },
     "scopesUri": "/rest/scopes/resources/rest/server-profiles/3c244628-0a0d-4ccd-a137-b77f639fe266",
     "serviceManager": null,
     "eTag": "1643405039788/44",
     "refreshState": "NotRefreshing"
}